{
    "translations_en": 
    [
        {
            "carte": "MENU A LA CARTE",
            "starter": "PRIMER PLAT",
            "item_1": "Raviolis de verdures amb salsa de formatge i llagostins.",
            "fish": "Peix",
            "item_2":"Corvall mediterrani amb anacards, olives negres, tomaques cherry confitades i alfabega.",
            "meat": "Carn",
            "item_3": "Espatlla de xai de llet a baixa temperatura amb alls i romaní.",
            "dessert": "POSTRES",
            "item_4": "Panacota de yogurt i gelé de fruits vermells.",
            "cake": "PASTIS",
            "item_5": "Brownie amb xocolata amb llet."
        }
    ]
}